<?xml version="1.0" encoding="UTF-8"?>
<objects serializationModel="Studio.02.02.00">
	<object class="ParameterPreset" id="{9b20654a-5bda-4ab6-abc5-dfc83773cb88}">
		<property name="name">
			<value>Throttle</value>
		</property>
		<relationship name="folder">
			<destination>{e17bc097-402e-48cf-9781-870d0d3b3a7a}</destination>
		</relationship>
		<relationship name="parameter">
			<destination>{4c165152-7c77-43a5-b967-1955eda301b4}</destination>
		</relationship>
	</object>
	<object class="GameParameter" id="{4c165152-7c77-43a5-b967-1955eda301b4}">
		<property name="initialValue">
			<value>0</value>
		</property>
		<property name="seekSpeed">
			<value>3.2000000476837158</value>
		</property>
	</object>
</objects>
